tree_units/__init__.py
tree_units/resources.py
tree_units/utils/__init__.py
tree_units/utils/_title_unit.py
tree_units/utils/get.py
tree_units/utils/layer.py
tree_units/utils/set.py
tree_units/utils/walk.py
tree_units-0.0.11.dist-info/WHEEL
tree_units-0.0.11.dist-info/METADATA
tree_units-0.0.11.dist-info/RECORD
