Metadata-Version: 2.1
Name: tree-units
Version: 0.0.11
Summary: Law mostly consists of tree-like nodes. This package supports a common tree format for Philippine Codifications, Statutes, and Documents, using a uniform node structure (i.e., leaves of a tree) identified by a given material path.
Author: Marcelino G. Veloso III
Author-email: mars@veloso.one
Requires-Python: >=3.10,<4.0
Classifier: Programming Language :: Python :: 3
Classifier: Programming Language :: Python :: 3.10
Classifier: Programming Language :: Python :: 3.11
Requires-Dist: citation-utils (>=0.0.13,<0.0.14)
Requires-Dist: email-validator (>=1.3.0,<2.0.0)
Requires-Dist: jinja2 (>=3.1.2,<4.0.0)
Requires-Dist: markdown (>=3.4.1,<4.0.0)
Requires-Dist: statute-utils (>=0.0.13,<0.0.14)
